CHANGES.txt
LICENSE.txt
MANIFEST.in
README.md
setup.py
cmsplugin_pagedown/__init__.py
cmsplugin_pagedown/cms_plugins.py
cmsplugin_pagedown/forms.py
cmsplugin_pagedown/models.py
cmsplugin_pagedown/tests.py
cmsplugin_pagedown/views.py
cmsplugin_pagedown.egg-info/PKG-INFO
cmsplugin_pagedown.egg-info/SOURCES.txt
cmsplugin_pagedown.egg-info/dependency_links.txt
cmsplugin_pagedown.egg-info/requires.txt
cmsplugin_pagedown.egg-info/top_level.txt
cmsplugin_pagedown/migrations/0001_initial.py
cmsplugin_pagedown/migrations/__init__.py
cmsplugin_pagedown/templates/cmsplugin_pagedown/markdown.html