Metadata-Version: 1.0
Name: cmsplugin-pagedown
Version: 0.0.1
Summary: A plugin for django-cms that includes the StackOverflow pagedown editor
Home-page: https://github.com/timmyomahony/cmsplugin-pagedown
Author: Timmy O'Mahony
Author-email: me@timmyomahony.com
License: LICENSE.txt
Platform: UNKNOWN
